napari_vesicles_segmentation/__init__.py
napari_vesicles_segmentation/_version.py
napari_vesicles_segmentation/_widget.py
napari_vesicles_segmentation/napari.yaml
napari_vesicles_segmentation/_tests/__init__.py
napari_vesicles_segmentation/_tests/test_widget.py
napari_vesicles_segmentation-0.0.1.dist-info/LICENSE
napari_vesicles_segmentation-0.0.1.dist-info/METADATA
napari_vesicles_segmentation-0.0.1.dist-info/WHEEL
napari_vesicles_segmentation-0.0.1.dist-info/entry_points.txt
napari_vesicles_segmentation-0.0.1.dist-info/top_level.txt
napari_vesicles_segmentation-0.0.1.dist-info/RECORD
