Metadata-Version: 2.1
Name: napari-vesicles-segmentation
Version: 0.0.1
Summary: A simple plugin to detect vesicles in cells images.
Home-page: https://github.com/alexisjapas/napari-vesicles-segmentation
Author: Alexis Japas
Author-email: alexis.japas@proton.me
License: BSD-3-Clause
Project-URL: Bug Tracker, https://github.com/alexisjapas/napari-vesicles-segmentation/issues
Project-URL: Documentation, https://github.com/alexisjapas/napari-vesicles-segmentation#README.md
Project-URL: Source Code, https://github.com/alexisjapas/napari-vesicles-segmentation
Project-URL: User Support, https://github.com/alexisjapas/napari-vesicles-segmentation/issues
Classifier: Development Status :: 2 - Pre-Alpha
Classifier: Framework :: napari
Classifier: Intended Audience :: Developers
Classifier: License :: OSI Approved :: BSD License
Classifier: Operating System :: OS Independent
Classifier: Programming Language :: Python
Classifier: Programming Language :: Python :: 3
Classifier: Programming Language :: Python :: 3 :: Only
Classifier: Programming Language :: Python :: 3.8
Classifier: Programming Language :: Python :: 3.9
Classifier: Programming Language :: Python :: 3.10
Classifier: Topic :: Scientific/Engineering :: Image Processing
Requires-Python: >=3.8
License-File: LICENSE
Requires-Dist: numpy
Requires-Dist: magicgui
Requires-Dist: qtpy
Requires-Dist: scikit-image
Requires-Dist: scipy
Provides-Extra: testing
Requires-Dist: tox ; extra == 'testing'
Requires-Dist: pytest ; extra == 'testing'
Requires-Dist: pytest-cov ; extra == 'testing'
Requires-Dist: pytest-qt ; extra == 'testing'
Requires-Dist: napari ; extra == 'testing'
Requires-Dist: pyqt5 ; extra == 'testing'
Requires-Dist: scikit-image ; extra == 'testing'
Requires-Dist: scipy ; extra == 'testing'
